ailetic/__init__.py
ailetic/file_handling.py
ailetic/main.py
ailetic/server.py
ailetic-0.1.0.dist-info/METADATA
ailetic-0.1.0.dist-info/WHEEL
ailetic-0.1.0.dist-info/entry_points.txt
ailetic-0.1.0.dist-info/top_level.txt
ailetic-0.1.0.dist-info/RECORD
