Metadata-Version: 2.1
Name: ailetic
Version: 0.1.0
Summary: UNKNOWN
Home-page: UNKNOWN
License: UNKNOWN
Platform: UNKNOWN
Requires-Dist: flask
Requires-Dist: flask-cors
Requires-Dist: numpy
Requires-Dist: Pillow
Requires-Dist: pydub
Requires-Dist: torch
Requires-Dist: torchvision
Requires-Dist: urllib3 ==1.26.6
